<?xml version="1.0" encoding="utf-8"?><Document><Engineering version="V17" /><DocumentInfo><Created>2023-04-06T14:59:51.4519566Z</Created><ExportSetting>None</ExportSetting><InstalledProducts><Product><DisplayName>Totally Integrated Automation Portal</DisplayName><DisplayVersion>V17 Update 4</DisplayVersion></Product><OptionPackage><DisplayName>TIA Portal Openness</DisplayName><DisplayVersion>V17 Update 4</DisplayVersion></OptionPackage><OptionPackage><DisplayName>TIA Portal Version Control Interface</DisplayName><DisplayVersion>V17</DisplayVersion></OptionPackage><Product><DisplayName>STEP 7 Professional</DisplayName><DisplayVersion>V17 Update 4</DisplayVersion></Product><OptionPackage><DisplayName>STEP 7 Safety</DisplayName><DisplayVersion>V17</DisplayVersion></OptionPackage><Product><DisplayName>WinCC Advanced / Unified PC</DisplayName><DisplayVersion>V17 Update 4</DisplayVersion></Product></InstalledProducts></DocumentInfo><SW.Blocks.GlobalDB ID="0"><AttributeList><AutoNumber>false</AutoNumber><Interface><Sections xmlns="http://www.siemens.com/automation/Openness/SW/Interface/v5"><Section Name="Static"><Member Name="PT_104" Datatype="Struct" Remanence="Retain"><Comment><MultiLanguageText Lang="en-US">GAS SUCTION PRESSURE</MultiLanguageText></Comment><Member Name="RANGE_L" Datatype="Real"><StartValue>-1.0</StartValue></Member><Member Name="RANGE_H" Datatype="Real"><StartValue>40.0</StartValue></Member><Member Name="SP_LL" Datatype="Real"><StartValue>-101.0</StartValue></Member><Member Name="SP_L" Datatype="Real"><StartValue>0.0</StartValue></Member><Member Name="SP_H" Datatype="Real"><StartValue>0.8</StartValue></Member><Member Name="SP_HH" Datatype="Real"><StartValue>140.0</StartValue></Member></Member><Member Name="TT_107_1" Datatype="Struct" Remanence="Retain"><Comment><MultiLanguageText Lang="en-US">GAS SUCTION TEMPERATURE</MultiLanguageText></Comment><Member Name="RANGE_L" Datatype="Real"><StartValue>-50.0</StartValue></Member><Member Name="RANGE_H" Datatype="Real"><StartValue>120.0</StartValue></Member><Member Name="SP_LL" Datatype="Real"><StartValue>-150.0</StartValue></Member><Member Name="SP_L" Datatype="Real"><StartValue>5.0</StartValue></Member><Member Name="SP_H" Datatype="Real"><StartValue>50.0</StartValue></Member><Member Name="SP_HH" Datatype="Real"><StartValue>220.0</StartValue></Member></Member><Member Name="PT_124" Datatype="Struct" Remanence="Retain"><Comment><MultiLanguageText Lang="en-US">GAS DISCHARGE PRESSURE</MultiLanguageText></Comment><Member Name="RANGE_L" Datatype="Real"><StartValue>-1.0</StartValue></Member><Member Name="RANGE_H" Datatype="Real"><StartValue>40.0</StartValue></Member><Member Name="SP_LL" Datatype="Real"><StartValue>-101.0</StartValue></Member><Member Name="SP_L" Datatype="Real"><StartValue>-101.0</StartValue></Member><Member Name="SP_H" Datatype="Real"><StartValue>22.4</StartValue></Member><Member Name="SP_HH" Datatype="Real"><StartValue>140.0</StartValue></Member></Member><Member Name="PDT_120" Datatype="Struct" Remanence="Retain"><Comment><MultiLanguageText Lang="en-US">DIFFERENTIAL PRESSURE GAS-OIL SEPARATOR</MultiLanguageText></Comment><Member Name="RANGE_L" Datatype="Real"><StartValue>0.0</StartValue></Member><Member Name="RANGE_H" Datatype="Real"><StartValue>1000.0</StartValue></Member><Member Name="SP_LL" Datatype="Real"><StartValue>-100.0</StartValue></Member><Member Name="SP_L" Datatype="Real"><StartValue>-100.0</StartValue></Member><Member Name="SP_H" Datatype="Real"><StartValue>250.0</StartValue></Member><Member Name="SP_HH" Datatype="Real"><StartValue>1100.0</StartValue></Member></Member><Member Name="PDT_121" Datatype="Struct" Remanence="Retain"><Comment><MultiLanguageText Lang="en-US">1st STAGE FILTER DIFFERENTIAL PRESSURE</MultiLanguageText></Comment><Member Name="RANGE_L" Datatype="Real"><StartValue>0.0</StartValue></Member><Member Name="RANGE_H" Datatype="Real"><StartValue>1000.0</StartValue></Member><Member Name="SP_LL" Datatype="Real"><StartValue>-100.0</StartValue></Member><Member Name="SP_L" Datatype="Real"><StartValue>-100.0</StartValue></Member><Member Name="SP_H" Datatype="Real"><StartValue>300.0</StartValue></Member><Member Name="SP_HH" Datatype="Real"><StartValue>1100.0</StartValue></Member></Member><Member Name="PDT_122" Datatype="Struct" Remanence="Retain"><Comment><MultiLanguageText Lang="en-US">2nd STAGE FILTER DIFFERENTIAL PRESSURE</MultiLanguageText></Comment><Member Name="RANGE_L" Datatype="Real"><StartValue>0.0</StartValue></Member><Member Name="RANGE_H" Datatype="Real"><StartValue>1000.0</StartValue></Member><Member Name="SP_LL" Datatype="Real"><StartValue>-100.0</StartValue></Member><Member Name="SP_L" Datatype="Real"><StartValue>-100.0</StartValue></Member><Member Name="SP_H" Datatype="Real"><StartValue>300.0</StartValue></Member><Member Name="SP_HH" Datatype="Real"><StartValue>1100.0</StartValue></Member></Member><Member Name="PDT_123" Datatype="Struct" Remanence="Retain"><Comment><MultiLanguageText Lang="en-US">3rd STAGE FILTER DIFFERENTIAL PRESSURE</MultiLanguageText></Comment><Member Name="RANGE_L" Datatype="Real"><StartValue>0.0</StartValue></Member><Member Name="RANGE_H" Datatype="Real"><StartValue>1000.0</StartValue></Member><Member Name="SP_LL" Datatype="Real"><StartValue>-100.0</StartValue></Member><Member Name="SP_L" Datatype="Real"><StartValue>-100.0</StartValue></Member><Member Name="SP_H" Datatype="Real"><StartValue>300.0</StartValue></Member><Member Name="SP_HH" Datatype="Real"><StartValue>1100.0</StartValue></Member></Member><Member Name="PDT_124" Datatype="Struct" Remanence="Retain"><Comment><MultiLanguageText Lang="en-US">4th STAGE FILTER DIFFERENTIAL PRESSURE</MultiLanguageText></Comment><Member Name="RANGE_L" Datatype="Real"><StartValue>0.0</StartValue></Member><Member Name="RANGE_H" Datatype="Real"><StartValue>1000.0</StartValue></Member><Member Name="SP_LL" Datatype="Real"><StartValue>-100.0</StartValue></Member><Member Name="SP_L" Datatype="Real"><StartValue>-100.0</StartValue></Member><Member Name="SP_H" Datatype="Real"><StartValue>300.0</StartValue></Member><Member Name="SP_HH" Datatype="Real"><StartValue>1100.0</StartValue></Member></Member><Member Name="GT_123_3" Datatype="Struct" Remanence="Retain"><Comment><MultiLanguageText Lang="en-US">RECYCLE VALVE POSITION FEEDBACK</MultiLanguageText></Comment><Member Name="RANGE_L" Datatype="Real"><StartValue>0.0</StartValue></Member><Member Name="RANGE_H" Datatype="Real"><StartValue>100.0</StartValue></Member><Member Name="SP_LL" Datatype="Real"><StartValue>-100.0</StartValue></Member><Member Name="SP_L" Datatype="Real"><StartValue>-100.0</StartValue></Member><Member Name="SP_H" Datatype="Real"><StartValue>200.0</StartValue></Member><Member Name="SP_HH" Datatype="Real"><StartValue>200.0</StartValue></Member></Member><Member Name="PDT_206" Datatype="Struct" Remanence="Retain"><Comment><MultiLanguageText Lang="en-US">PRIMARY OIL FILTER DIFFERENTIAL PRESSURE</MultiLanguageText></Comment><Member Name="RANGE_L" Datatype="Real"><StartValue>0.0</StartValue></Member><Member Name="RANGE_H" Datatype="Real"><StartValue>1000.0</StartValue></Member><Member Name="SP_LL" Datatype="Real"><StartValue>-100.0</StartValue></Member><Member Name="SP_L" Datatype="Real"><StartValue>-100.0</StartValue></Member><Member Name="SP_H" Datatype="Real"><StartValue>500.0</StartValue></Member><Member Name="SP_HH" Datatype="Real"><StartValue>1100.0</StartValue></Member></Member><Member Name="GT_450_3" Datatype="Struct" Remanence="Retain"><Comment><MultiLanguageText Lang="en-US">WATER CONTROL VALVE POSITION FEEDBACK</MultiLanguageText></Comment><Member Name="RANGE_L" Datatype="Real"><StartValue>0.0</StartValue></Member><Member Name="RANGE_H" Datatype="Real"><StartValue>100.0</StartValue></Member><Member Name="SP_LL" Datatype="Real"><StartValue>-100.0</StartValue></Member><Member Name="SP_L" Datatype="Real"><StartValue>-100.0</StartValue></Member><Member Name="SP_H" Datatype="Real"><StartValue>200.0</StartValue></Member><Member Name="SP_HH" Datatype="Real"><StartValue>200.0</StartValue></Member></Member><Member Name="GT_440" Datatype="Struct" Remanence="Retain"><Comment><MultiLanguageText Lang="en-US">WATER CONTROL VALVE POSITION FEEDBACK</MultiLanguageText></Comment><Member Name="RANGE_L" Datatype="Real"><StartValue>0.0</StartValue></Member><Member Name="RANGE_H" Datatype="Real"><StartValue>100.0</StartValue></Member><Member Name="SP_LL" Datatype="Real"><StartValue>-100.0</StartValue></Member><Member Name="SP_L" Datatype="Real"><StartValue>-100.0</StartValue></Member><Member Name="SP_H" Datatype="Real"><StartValue>200.0</StartValue></Member><Member Name="SP_HH" Datatype="Real"><StartValue>200.0</StartValue></Member></Member><Member Name="GT_168" Datatype="Struct" Remanence="Retain"><Comment><MultiLanguageText Lang="en-US">SLIDE VALVE POSITION FEEDBACK </MultiLanguageText></Comment><Member Name="RANGE_L" Datatype="Real"><StartValue>0.0</StartValue></Member><Member Name="RANGE_H" Datatype="Real"><StartValue>100.0</StartValue></Member><Member Name="SP_LL" Datatype="Real"><StartValue>-100.0</StartValue></Member><Member Name="SP_L" Datatype="Real"><StartValue>35.0</StartValue></Member><Member Name="SP_H" Datatype="Real"><StartValue>200.0</StartValue></Member><Member Name="SP_HH" Datatype="Real"><StartValue>200.0</StartValue></Member></Member><Member Name="TT_125" Datatype="Struct" Remanence="Retain"><Comment><MultiLanguageText Lang="en-US">GAS TEMPERATURE DOWNSTREAM GAS COOLER</MultiLanguageText></Comment><Member Name="RANGE_L" Datatype="Real"><StartValue>-50.0</StartValue></Member><Member Name="RANGE_H" Datatype="Real"><StartValue>120.0</StartValue></Member><Member Name="SP_LL" Datatype="Real"><StartValue>-150.0</StartValue></Member><Member Name="SP_L" Datatype="Real"><StartValue>15.0</StartValue></Member><Member Name="SP_H" Datatype="Real"><StartValue>50.0</StartValue></Member><Member Name="SP_HH" Datatype="Real"><StartValue>220.0</StartValue></Member></Member><Member Name="KF_401" Datatype="Struct" Remanence="Retain"><Comment><MultiLanguageText Lang="en-US">SET SLIDE POSITION</MultiLanguageText></Comment><Member Name="RANGE_L" Datatype="Real"><StartValue>0.0</StartValue></Member><Member Name="RANGE_H" Datatype="Real"><StartValue>100.0</StartValue></Member><Member Name="SP_LL" Datatype="Real"><StartValue>-100.0</StartValue></Member><Member Name="SP_L" Datatype="Real"><StartValue>-100.0</StartValue></Member><Member Name="SP_H" Datatype="Real"><StartValue>200.0</StartValue></Member><Member Name="SP_HH" Datatype="Real"><StartValue>200.0</StartValue></Member></Member><Member Name="KF_408" Datatype="Struct" Remanence="Retain"><Comment><MultiLanguageText Lang="en-US">SET RECYCLE VALVE POSITION</MultiLanguageText></Comment><Member Name="RANGE_L" Datatype="Real"><StartValue>0.0</StartValue></Member><Member Name="RANGE_H" Datatype="Real"><StartValue>100.0</StartValue></Member><Member Name="SP_LL" Datatype="Real"><StartValue>-100.0</StartValue></Member><Member Name="SP_L" Datatype="Real"><StartValue>-100.0</StartValue></Member><Member Name="SP_H" Datatype="Real"><StartValue>200.0</StartValue></Member><Member Name="SP_HH" Datatype="Real"><StartValue>200.0</StartValue></Member></Member><Member Name="PGP_202" Datatype="Struct" Remanence="Retain"><Comment><MultiLanguageText Lang="en-US">CALCULATED OIL - GAS PRESSURE RATIO (PT124 / PT105)</MultiLanguageText></Comment><Member Name="RANGE_L" Datatype="Real"><StartValue>0.5</StartValue></Member><Member Name="RANGE_H" Datatype="Real"><StartValue>25.0</StartValue></Member><Member Name="SP_LL" Datatype="Real"><StartValue>1.5</StartValue></Member><Member Name="SP_L" Datatype="Real"><StartValue>1.5</StartValue></Member><Member Name="SP_H" Datatype="Real"><StartValue>20.0</StartValue></Member><Member Name="SP_HH" Datatype="Real"><StartValue>23.0</StartValue></Member></Member><Member Name="PDP_203" Datatype="Struct" Remanence="Retain"><Comment><MultiLanguageText Lang="en-US">CALCULATED COMPRESSOR DIFFERENTIAL PRESSURE (PT124 - PT105)</MultiLanguageText></Comment><Member Name="RANGE_L" Datatype="Real"><StartValue>0.5</StartValue></Member><Member Name="RANGE_H" Datatype="Real"><StartValue>25.0</StartValue></Member><Member Name="SP_LL" Datatype="Real"><StartValue>3.0</StartValue></Member><Member Name="SP_L" Datatype="Real"><StartValue>3.5</StartValue></Member><Member Name="SP_H" Datatype="Real"><StartValue>125.0</StartValue></Member><Member Name="SP_HH" Datatype="Real"><StartValue>125.0</StartValue></Member></Member><Member Name="PT_105" Datatype="Struct" Remanence="Retain"><Comment><MultiLanguageText Lang="en-US">GAS SUCTION PRESSURE</MultiLanguageText></Comment><Member Name="RANGE_L" Datatype="Real"><StartValue>-1.0</StartValue></Member><Member Name="RANGE_H" Datatype="Real"><StartValue>40.0</StartValue></Member><Member Name="SP_LL" Datatype="Real"><StartValue>0.3</StartValue></Member><Member Name="SP_L" Datatype="Real"><StartValue>-101.0</StartValue></Member><Member Name="SP_H" Datatype="Real"><StartValue>140.0</StartValue></Member><Member Name="SP_HH" Datatype="Real"><StartValue>1.2</StartValue></Member></Member><Member Name="PT_113" Datatype="Struct" Remanence="Retain"><Comment><MultiLanguageText Lang="en-US">GAS DISCHARGE PRESSURE</MultiLanguageText></Comment><Member Name="RANGE_L" Datatype="Real"><StartValue>-1.0</StartValue></Member><Member Name="RANGE_H" Datatype="Real"><StartValue>40.0</StartValue></Member><Member Name="SP_LL" Datatype="Real"><StartValue>-101.0</StartValue></Member><Member Name="SP_L" Datatype="Real"><StartValue>-101.0</StartValue></Member><Member Name="SP_H" Datatype="Real"><StartValue>22.7</StartValue></Member><Member Name="SP_HH" Datatype="Real"><StartValue>23.0</StartValue></Member></Member><Member Name="TT_114" Datatype="Struct" Remanence="Retain"><Comment><MultiLanguageText Lang="en-US">GAS DISCHARGE TEMPERATURE</MultiLanguageText></Comment><Member Name="RANGE_L" Datatype="Real"><StartValue>-50.0</StartValue></Member><Member Name="RANGE_H" Datatype="Real"><StartValue>120.0</StartValue></Member><Member Name="SP_LL" Datatype="Real"><StartValue>-150.0</StartValue></Member><Member Name="SP_L" Datatype="Real"><StartValue>-150.0</StartValue></Member><Member Name="SP_H" Datatype="Real"><StartValue>110.0</StartValue></Member><Member Name="SP_HH" Datatype="Real"><StartValue>115.0</StartValue></Member></Member><Member Name="TT_128" Datatype="Struct" Remanence="Retain"><Comment><MultiLanguageText Lang="en-US">GAS TEMPERATURE DOWNSTREAM GAS COOLER</MultiLanguageText></Comment><Member Name="RANGE_L" Datatype="Real"><StartValue>-50.0</StartValue></Member><Member Name="RANGE_H" Datatype="Real"><StartValue>120.0</StartValue></Member><Member Name="SP_LL" Datatype="Real"><StartValue>-150.0</StartValue></Member><Member Name="SP_L" Datatype="Real"><StartValue>-150.0</StartValue></Member><Member Name="SP_H" Datatype="Real"><StartValue>220.0</StartValue></Member><Member Name="SP_HH" Datatype="Real"><StartValue>60.0</StartValue></Member></Member><Member Name="TT_208" Datatype="Struct" Remanence="Retain"><Comment><MultiLanguageText Lang="en-US">LUBE OIL TEMPERATURE </MultiLanguageText></Comment><Member Name="RANGE_L" Datatype="Real"><StartValue>-50.0</StartValue></Member><Member Name="RANGE_H" Datatype="Real"><StartValue>120.0</StartValue></Member><Member Name="SP_LL" Datatype="Real"><StartValue>-150.0</StartValue></Member><Member Name="SP_L" Datatype="Real"><StartValue>25.0</StartValue></Member><Member Name="SP_H" Datatype="Real"><StartValue>65.0</StartValue></Member><Member Name="SP_HH" Datatype="Real"><StartValue>70.0</StartValue></Member></Member><Member Name="PT_501" Datatype="Struct" Remanence="Retain"><Comment><MultiLanguageText Lang="en-US">INSTRUMENT AIR PRESSURE</MultiLanguageText></Comment><Member Name="RANGE_L" Datatype="Real"><StartValue>-1.0</StartValue></Member><Member Name="RANGE_H" Datatype="Real"><StartValue>40.0</StartValue></Member><Member Name="SP_LL" Datatype="Real"><StartValue>4.5</StartValue></Member><Member Name="SP_L" Datatype="Real"><StartValue>-101.0</StartValue></Member><Member Name="SP_H" Datatype="Real"><StartValue>140.0</StartValue></Member><Member Name="SP_HH" Datatype="Real"><StartValue>26.0</StartValue></Member></Member><Member Name="VT_111_13" Datatype="Struct" Remanence="Retain"><Comment><MultiLanguageText Lang="en-US">COMPRESSOR HOUSING VIBRATION</MultiLanguageText></Comment><Member Name="RANGE_L" Datatype="Real"><StartValue>0.0</StartValue></Member><Member Name="RANGE_H" Datatype="Real"><StartValue>25.4</StartValue></Member><Member Name="SP_LL" Datatype="Real"><StartValue>-100.0</StartValue></Member><Member Name="SP_L" Datatype="Real"><StartValue>-100.0</StartValue></Member><Member Name="SP_H" Datatype="Real"><StartValue>4.5</StartValue></Member><Member Name="SP_HH" Datatype="Real"><StartValue>6.0</StartValue></Member></Member><Member Name="VT_112_13" Datatype="Struct" Remanence="Retain"><Comment><MultiLanguageText Lang="en-US">MAIN MOTOR BEARING  DE VIBRATION</MultiLanguageText></Comment><Member Name="RANGE_L" Datatype="Real"><StartValue>0.0</StartValue></Member><Member Name="RANGE_H" Datatype="Real"><StartValue>25.4</StartValue></Member><Member Name="SP_LL" Datatype="Real"><StartValue>-100.0</StartValue></Member><Member Name="SP_L" Datatype="Real"><StartValue>-100.0</StartValue></Member><Member Name="SP_H" Datatype="Real"><StartValue>4.5</StartValue></Member><Member Name="SP_HH" Datatype="Real"><StartValue>6.0</StartValue></Member></Member><Member Name="VT_112_14" Datatype="Struct" Remanence="Retain"><Comment><MultiLanguageText Lang="en-US">MAIN MOTOR BEARING NDE VIBRATION</MultiLanguageText></Comment><Member Name="RANGE_L" Datatype="Real"><StartValue>0.0</StartValue></Member><Member Name="RANGE_H" Datatype="Real"><StartValue>25.4</StartValue></Member><Member Name="SP_LL" Datatype="Real"><StartValue>-100.0</StartValue></Member><Member Name="SP_L" Datatype="Real"><StartValue>-100.0</StartValue></Member><Member Name="SP_H" Datatype="Real"><StartValue>4.5</StartValue></Member><Member Name="SP_HH" Datatype="Real"><StartValue>6.0</StartValue></Member></Member><Member Name="TE_112_5_I" Datatype="Struct" Remanence="Retain"><Comment><MultiLanguageText Lang="en-US">MAIN MOTOR WINDING TEMPERATURE U</MultiLanguageText></Comment><Member Name="RANGE_L" Datatype="Real"><StartValue>0.0</StartValue></Member><Member Name="RANGE_H" Datatype="Real"><StartValue>200.0</StartValue></Member><Member Name="SP_LL" Datatype="Real"><StartValue>-100.0</StartValue></Member><Member Name="SP_L" Datatype="Real"><StartValue>-100.0</StartValue></Member><Member Name="SP_H" Datatype="Real"><StartValue>130.0</StartValue></Member><Member Name="SP_HH" Datatype="Real"><StartValue>145.0</StartValue></Member></Member><Member Name="TE_112_6_I" Datatype="Struct" Remanence="Retain"><Comment><MultiLanguageText Lang="en-US">MAIN MOTOR WINDING TEMPERATURE V</MultiLanguageText></Comment><Member Name="RANGE_L" Datatype="Real"><StartValue>0.0</StartValue></Member><Member Name="RANGE_H" Datatype="Real"><StartValue>200.0</StartValue></Member><Member Name="SP_LL" Datatype="Real"><StartValue>-100.0</StartValue></Member><Member Name="SP_L" Datatype="Real"><StartValue>-100.0</StartValue></Member><Member Name="SP_H" Datatype="Real"><StartValue>130.0</StartValue></Member><Member Name="SP_HH" Datatype="Real"><StartValue>145.0</StartValue></Member></Member><Member Name="TE_112_7_I" Datatype="Struct" Remanence="Retain"><Comment><MultiLanguageText Lang="en-US">MAIN MOTOR WINDING TEMPERATURE W</MultiLanguageText></Comment><Member Name="RANGE_L" Datatype="Real"><StartValue>0.0</StartValue></Member><Member Name="RANGE_H" Datatype="Real"><StartValue>200.0</StartValue></Member><Member Name="SP_LL" Datatype="Real"><StartValue>-100.0</StartValue></Member><Member Name="SP_L" Datatype="Real"><StartValue>-100.0</StartValue></Member><Member Name="SP_H" Datatype="Real"><StartValue>130.0</StartValue></Member><Member Name="SP_HH" Datatype="Real"><StartValue>145.0</StartValue></Member></Member></Section></Sections></Interface><MemoryLayout>Standard</MemoryLayout><Name>SETTINGS</Name><Number>26</Number><ProgrammingLanguage>DB</ProgrammingLanguage></AttributeList><ObjectList><MultilingualText ID="1" CompositionName="Comment"><ObjectList><MultilingualTextItem ID="2" CompositionName="Items"><AttributeList><Culture>en-US</Culture><Text /></AttributeList></MultilingualTextItem></ObjectList></MultilingualText><MultilingualText ID="3" CompositionName="Title"><ObjectList><MultilingualTextItem ID="4" CompositionName="Items"><AttributeList><Culture>en-US</Culture><Text /></AttributeList></MultilingualTextItem></ObjectList></MultilingualText></ObjectList></SW.Blocks.GlobalDB></Document>